geniectl/__init__.py
geniectl/cli.py
geniectl/engine.py
geniectl/exceptions.py
geniectl/parser.py
geniectl/kinds/__init__.py
geniectl/kinds/audio.py
geniectl/kinds/base.py
geniectl/kinds/custom_gemini_cli.py
geniectl/kinds/gemini_cli.py
geniectl/kinds/image.py
geniectl/kinds/music.py
geniectl/kinds/text.py
geniectl/kinds/text_test.py
geniectl-0.8.0.dist-info/licenses/LICENSE
geniectl-0.8.0.dist-info/METADATA
geniectl-0.8.0.dist-info/WHEEL
geniectl-0.8.0.dist-info/entry_points.txt
geniectl-0.8.0.dist-info/top_level.txt
geniectl-0.8.0.dist-info/RECORD
